doodaw/main.py
doodaw-0.1.1.dist-info/WHEEL
doodaw-0.1.1.dist-info/METADATA
doodaw-0.1.1.dist-info/RECORD
