Metadata-Version: 2.1
Name: doodaw
Version: 0.1.1
Summary: A Discord bot
